{
  "results": [
    {
      "result": "```markdown\n# School Data Enrichment Report\n## Summary\n- Total Schools Processed: 2\n- Successfully Updated: 0\n- Failed Updates: 2\n\n## Details\n1. SACRED HEART CATHOLIC HIGH SCHOOL (ee8981ae-7f29-47bf-968c-4829381e0559)\n   - Total Student Enrollment: Missing or Invalid\n   - Latitude: 35.153045\n   - Longitude: -92.740309\n   - Status: Failed Update\n\n2. LITTLE FISHERS PRESCHOOL (e6595f1f-fe60-4678-8d75-fadc940c1945)\n   - Total Student Enrollment: Missing or Invalid\n   - Latitude: 29.586609\n   - Longitude: -95.618186\n   - Status: Failed Update\n\n## Recommendations\n- Verify and update the Total Student Enrollment data\n```",
      "raw_output": null,
      "task_outputs": []
    }
  ],
  "total_batches": 1
}